<?xml version='1.0' encoding='GBK'?><mdroot><grdds>
<ROWSET>
<ROW num="0" ><MWTYP >R</MWTYP><MWID >CX_J3ZGSJZLJXKHZB</MWID><NAME >金税三期核心征管数据质量绩效考核指标</NAME><NOTE ></NOTE><NOACCNAME ></NOACCNAME><FILE >CX_J3ZGSJZLJXKHZB.zxg</FILE><SCENE ></SCENE><FIXED ></FIXED><CATTYP ></CATTYP><DTLRNG ></DTLRNG><BATINP ></BATINP><MANUNIT ></MANUNIT><USESMLUNT ></USESMLUNT><ITEMTABLE ></ITEMTABLE><BILHDRTABLE ></BILHDRTABLE><BILDTLTABLE ></BILDTLTABLE><COLLIST ></COLLIST><WHERE ></WHERE><ORDER ></ORDER><DBNAME ></DBNAME><LISTSUM ></LISTSUM><LOADDATA ></LOADDATA><CHECKTITLE ></CHECKTITLE><IFBILL ></IFBILL><EXTJS ></EXTJS><JAVACLS ></JAVACLS><POST2MWID ></POST2MWID><LMS ></LMS><WIDTHMOD ></WIDTHMOD><HEIGHTMOD ></HEIGHTMOD><CLIENTCLASS ></CLIENTCLASS><SHOWBTN >0</SHOWBTN><CLOSEPAGES ></CLOSEPAGES><syt >TAXFXJK</syt></ROW>
</ROWSET>
</grdds><grdbtnds>
<ROWSET>
<ROW num="0" ><ID >newRow</ID><NAME >新增</NAME><ACTTYP ></ACTTYP><URL ></URL><URLTARGET ></URLTARGET><TIP ></TIP><BTNORD ></BTNORD><IMG >4</IMG><IMGMOUSE >4</IMGMOUSE><C10 >GRDBTNDS_0</C10></ROW>
<ROW num="1" ><ID >deleteRow</ID><NAME >删除</NAME><ACTTYP ></ACTTYP><URL ></URL><URLTARGET ></URLTARGET><TIP ></TIP><BTNORD ></BTNORD><IMG >2</IMG><IMGMOUSE >2</IMGMOUSE><C10 >GRDBTNDS_1</C10></ROW>
</ROWSET>
</grdbtnds><grdshwds>
<ROWSET>
<ROW num="0" ><ID >0,1,1</ID><NAME ></NAME><DBNAME ></DBNAME><DSKEY >DSC:MAIN</DSKEY><NROW >3</NROW><NCOL >10</NCOL><PAGES ></PAGES><PAGESIZE ></PAGESIZE><URL ></URL><CTLTYP ></CTLTYP><DYNCTL ></DYNCTL><LISTID ></LISTID><ISCROSS ></ISCROSS><HROW ></HROW><HCOLS ></HCOLS><ROWORDER ></ROWORDER><VCOLS ></VCOLS><VCOLSQL ></VCOLSQL><VALUECOL ></VALUECOL><C20 >0,1,0</C20></ROW>
</ROWSET>
</grdshwds><grdjsds>
<ROWSET>
<ROW num="0" ><GRDJSDS_VALUE >
//数据加载完毕
function _thisOnpost_loaddata(sheet)
{
	_this.SetColVisible(0,1,-1);
	_this.SetColVisible(0,3,-1);
	_this.SetColVisible(0,5,-1);
	_this.SetColVisible(0,10,-1);
	_this.SetAttribe(&amp;quot;SHEET_0&amp;quot;,_this.ATTR_SHEET_SELECTFLAG,_this.SELECTFLAG_SINGLEROW);
	_this.SetToBoolBox(0,0,0);
	for (var r=1;r&amp;lt;_this.GetRowCount(0);r++) {
		_this.SetToBoolBox(0,r,0);
		_this.SetToBoolBox(0,r,8);
		_this.SetToButton(&amp;quot;&amp;quot;,0,r,9,&amp;quot;打开报表&amp;quot;,&amp;quot;打开报表&amp;quot;,&amp;quot;&amp;quot;,0,-1,-1);
	}
	_this.AutoFixScreenWidth();
}

//点击按钮
function _thisOnButtonCtrlClick(id,sheet,row,col)
{
	if (sheet == 0) {
		if (id.indexOf(&amp;quot;CELL_0&amp;quot;) &amp;gt; -1) {
			//var url = _this.GetCellText(sheet,row,10); //url
			var id = _this.GetCellText(sheet,row,6);
			var url = &amp;quot;show.sp?grdid=&amp;quot;+id;
			window.open(url);
		}
	}
}

//修改单元格内容
function _thisOnCellModify(sheet,row,col,oldvalue,newvalue)
{
	if (sheet == 0 &amp;&amp; row == 0 &amp;&amp; col == 0) {
		for (var r=1;r&amp;lt;_this.GetRowCount(0);r++) {
			_this.SetCellText(0,r,0,newvalue);
		}
	}
}

//鼠标双击
function _thisOnMouseDClick(sheet,row,col)
{
	if (sheet == 0 &amp;&amp; row &amp;gt;= _this.GetMainCellRangeRow1(0) &amp;&amp; row &amp;lt;= _this.GetMainCellRangeRow2(0)) {
		var id = _this.GetCellText(sheet,row,6);
		var url = &amp;quot;show.sp?grdid=&amp;quot;+id;
		window.open(url);
	}
}
</GRDJSDS_VALUE></ROW>
</ROWSET>
</grdjsds><grdosds>
<ROWSET>
<ROW num="0" ><GRDOSDS_VALUE ></GRDOSDS_VALUE></ROW>
</ROWSET>
</grdosds><grddscds>
<ROWSET>
<ROW num="0" ><ID >MAIN</ID><NAME ></NAME><DATDSC >select guid,rownum,dl,zl,xl,flbh,flmc,yxbz,&amp;apos;打开报表&amp;apos; action,url 
from (
select * 
from FXJK_ITEM
where typ=&amp;apos;1&amp;apos;
order by flbh
)</DATDSC><C4 >MAIN</C4><C5 >MAIN</C5></ROW>
</ROWSET>
</grddscds><fldhdr>
<ROWSET>
<ROW num="0" ><BILID >1单据编号</BILID><STAT >0单据状态</STAT><SUBTYP >0子类型</SUBTYP><CORPID >0往来单位编号</CORPID><CORPNAM >0往来单位名称</CORPNAM><LOCID >0仓库|部门编号</LOCID><LOCNAM >0仓库|部门名称</LOCNAM><DAT >0单据日期</DAT><CRTUSR >1录入人</CRTUSR><CRTUSRNAM >0录入人姓名</CRTUSRNAM><CRTDAT >0录入日期</CRTDAT><CHKUSR >1审核人</CHKUSR><CHKUSRNAM >0审核人姓名</CHKUSRNAM><CHKDAT >0审核日期</CHKDAT><SUMQTY >0合计金额</SUMQTY><SUMMNY >0合计金额</SUMMNY><REFID1 >0扩展字段</REFID1><REFNAM1 >0扩展字段</REFNAM1><REFID2 >0扩展字段</REFID2><REFNAM2 >0扩展字段</REFNAM2><REFID3 >0扩展字段</REFID3><REFNAM3 >0扩展字段</REFNAM3><REFID4 >0扩展字段</REFID4><REFNAM4 >0扩展字段</REFNAM4><REFID5 >0扩展字段</REFID5><REFNAM5 >0扩展字段</REFNAM5><REFID6 >0扩展字段</REFID6><REFNAM6 >0扩展字段</REFNAM6><NOTE >0备注</NOTE></ROW>
</ROWSET>
</fldhdr><flddtl>
<ROWSET>
<ROW num="0" ><SEQID >1明细序号</SEQID><ITMID >1品种编号</ITMID><ITMNAM >0品种名称</ITMNAM><ITEMPC >0品种批次号</ITEMPC><ITMSPC >0规格</ITMSPC><UNIT >0计量单位</UNIT><SMLUNT >0小计量单位</SMLUNT><UNTNUM >0大单位转小单位因子</UNTNUM><PRICE >0价格</PRICE><QTY >0数量</QTY><TAXTYP >0税率类型</TAXTYP><NOTAXMNY >0不含税税额</NOTAXMNY><TAXMNY >0税额</TAXMNY><MNY >0下单金额</MNY><REFID1 >0扩展字段</REFID1><REFNAM1 >0扩展字段</REFNAM1><REFID2 >0扩展字段</REFID2><REFNAM2 >0扩展字段</REFNAM2><REFID3 >0扩展字段</REFID3><REFNAM3 >0扩展字段</REFNAM3><REFID4 >0扩展字段</REFID4><REFNAM4 >0扩展字段</REFNAM4><REFID5 >0扩展字段</REFID5><REFNAM5 >0扩展字段</REFNAM5></ROW>
</ROWSET>
</flddtl></mdroot>